utility_lens/__init__.py
utility_lens/analysis/__init__.py
utility_lens/analysis/iia.py
utility_lens/analysis/transitivity.py
utility_lens/analysis/utility.py
utility_lens/models/__init__.py
utility_lens/models/base.py
utility_lens/models/local.py
utility_lens/models/openai.py
utility_lens-0.1.3.dist-info/METADATA
utility_lens-0.1.3.dist-info/WHEEL
utility_lens-0.1.3.dist-info/RECORD
