Metadata-Version: 2.1
Name: utility-lens
Version: 0.1.3
Summary: 
Author: Bruce W. Lee
Author-email: phys.w.s.lee@gmail.com
Requires-Python: >=3.9,<4.0
Classifier: Programming Language :: Python :: 3
Classifier: Programming Language :: Python :: 3.9
Classifier: Programming Language :: Python :: 3.10
Classifier: Programming Language :: Python :: 3.11
Classifier: Programming Language :: Python :: 3.12
Requires-Dist: openai (>=1.55.1,<2.0.0)
Requires-Dist: tqdm (>=4.67.1,<5.0.0)
